kdump/__init__.py
kdump/classlist.py
kdump/headers.py
kdump/ninja_generator.py
kdump/sdkbuilder.py
kdump/macho/__init__.py
kdump/macho/binding.py
kdump/macho/macho.py
kdump/macho/segment.py
kdump/macho/structs.py
kdump/macho/util.py
kdump/macho/vm.py
kdump/objectivec/__init__.py
kdump/objectivec/ivar.py
kdump/objectivec/method.py
kdump/objectivec/objcclass.py
kdump/objectivec/property.py
kdump/objectivec/protocol.py
kdump/objectivec/structs.py
kdump/objectivec/type.py
kdump-0.1.0.data/scripts/kdump
kdump-0.1.0.dist-info/LICENSE
kdump-0.1.0.dist-info/METADATA
kdump-0.1.0.dist-info/WHEEL
kdump-0.1.0.dist-info/top_level.txt
kdump-0.1.0.dist-info/RECORD
