Metadata-Version: 2.1
Name: kdump
Version: 0.1.0
Summary: Static mach-o binary analysis tool.
Home-page: https://github.com/kritantadev/kdump
Author: _kritanta
Author-email: krit@krit.me
License: UNKNOWN
Project-URL: Bug Tracker, https://github.com/kritantadev/kdump/issues
Platform: UNKNOWN
Classifier: Programming Language :: Python :: 3
Classifier: License :: OSI Approved :: MIT License
Classifier: Operating System :: OS Independent
Requires-Python: >=3.6
License-File: LICENSE
